kuku/__init__.py
kuku/__version__.py
kuku/cli.py
kuku/dump.py
kuku/render.py
kuku/templates.py
kuku/types.py
kuku/values.py
kuku/tests/__init__.py
kuku/tests/test_dump.py
kuku/tests/test_render.py
kuku/tests/test_templates.py
kuku/tests/test_values.py
kuku/tests/fixtures/__init__.py
kuku/tests/fixtures/templates/__init__.py
kuku/tests/fixtures/templates/namespace.py
kuku/tests/fixtures/templates/not_template.py
kuku/tests/fixtures/templates/service.py
kuku/utils/__init__.py
kuku/utils/dict.py
kuku/utils/str.py
kuku/utils/yaml.py
kuku-0.1.2.dist-info/LICENSE
kuku-0.1.2.dist-info/METADATA
kuku-0.1.2.dist-info/WHEEL
kuku-0.1.2.dist-info/entry_points.txt
kuku-0.1.2.dist-info/top_level.txt
kuku-0.1.2.dist-info/RECORD
